im_futuretest/__init__.py
im_futuretest/model.py
im_futuretest/web/future.js
im_futuretest/web/futuretop.js
im_futuretest/web/main.css
im_futuretest/web/main.js
im_futuretest/web/runslistitem.js
im_futuretest/web/spa.html
im_futuretest/web/test.js
im_futuretest/web/testlistitem.js
im_futuretest/web/tests.js
im_futuretest-0.1.14.dist-info/DESCRIPTION.rst
im_futuretest-0.1.14.dist-info/METADATA
im_futuretest-0.1.14.dist-info/RECORD
im_futuretest-0.1.14.dist-info/WHEEL
im_futuretest-0.1.14.dist-info/metadata.json
im_futuretest-0.1.14.dist-info/top_level.txt
