Metadata-Version: 2.0
Name: im-futuretest
Version: 0.1.14
Summary: This package provides a pre-packaged UI for running tests based on @futures, in Google App Engine, Python standard environment projects.
Home-page: https://github.com/emlynoregan/im_futuretest
Author: Emlyn O'Regan
Author-email: emlynoregan@gmail.com
License: ../LICENSE.txt
Platform: UNKNOWN
Classifier: Development Status :: 3 - Alpha
Classifier: Intended Audience :: Developers
Classifier: License :: OSI Approved :: Apache Software License
Classifier: Operating System :: POSIX
Classifier: Operating System :: Microsoft :: Windows
Classifier: Operating System :: MacOS :: MacOS X
Classifier: Programming Language :: Python :: 2.7
Classifier: Programming Language :: Python :: Implementation :: CPython
Classifier: Topic :: Software Development :: Libraries :: Python Modules
Classifier: Topic :: System :: Distributed Computing
Requires-Dist: im-util (>=0.1.4)
Requires-Dist: im-future (>=0.1.1)
Requires-Dist: im-debouncedtask
